{
  ".*kanker.*": [
    "Kanker adalah penyakit ganas yang disebabkan oleh pertumbuhan sel-sel yang tidak normal.",
    "Ada berbagai jenis kanker, termasuk kanker payudara, kanker paru-paru, dan lain-lain.",
    "Pencegahan kanker meliputi gaya hidup sehat dan deteksi dini.",
    "Pengobatan kanker dapat melibatkan operasi, kemoterapi, dan radioterapi."
  ],
  ".*presiden.*indonesia.*": [
    "Presiden Indonesia saat ini adalah Joko Widodo, yang mulai menjabat pada tahun 2014.",
    "Presiden Indonesia sebelumnya adalah Susilo Bambang Yudhoyono, yang menjabat dari tahun 2004 hingga 2014.",
    "Indonesia adalah negara demokrasi dengan presiden sebagai kepala negara dan pemerintahan."
  ],
  ".*siapa.*artis.*terkenal.*indonesia.*": [
    "Beberapa artis terkenal di Indonesia antara lain Raffi Ahmad, Raisa, dan Agnes Monica.",
    "Dalam dunia seni dan hiburan, Indonesia memiliki berbagai bakat yang mendunia.",
    "Artis-artis Indonesia sering kali dikenal baik di dalam negeri maupun internasional."
  ],
  ".*presiden.*uganda.*": [
    "Presiden Uganda saat ini adalah Yoweri Museveni, yang telah menjabat sejak tahun 1986.",
    "Museveni adalah salah satu pemimpin terpanjang di Afrika dan sering kali kontroversial dalam politiknya."
  ],
  ".*presiden.*malaysia.*": [
    "Presiden Malaysia saat ini adalah Sultan Abdullah Sultan Ahmad Shah, yang mulai menjabat pada tahun 2019.",
    "Malaysia memiliki sistem monarki konstitusional, di mana jabatan presiden sering kali dipegang oleh sultan-sultan dari negara bagian Malaysia."
  ]
}
